etomofiles/__init__.py
etomofiles/imod_utils.py
etomofiles/io.py
etomofiles/utils.py
etomofiles/data_model/__init__.py
etomofiles/data_model/etomo_data.py
etomofiles-0.1.1.dist-info/METADATA
etomofiles-0.1.1.dist-info/WHEEL
etomofiles-0.1.1.dist-info/licenses/LICENSE
etomofiles-0.1.1.dist-info/RECORD
