Metadata-Version: 2.4
Name: etomofiles
Version: 0.1.1
Summary: A Python package for reading IMOD etomo alignment files into pandas DataFrames
Project-URL: homepage, https://github.com/teamtomo/etomofiles
Project-URL: repository, https://github.com/teamtomo/etomofiles
Project-URL: issues, https://github.com/teamtomo/etomofiles/issues
Author-email: Davide Torre <davidetorre99@gmail.com>
License: BSD-3-Clause
License-File: LICENSE
Classifier: Development Status :: 4 - Beta
Classifier: License :: OSI Approved :: BSD License
Classifier: Programming Language :: Python :: 3
Classifier: Programming Language :: Python :: 3.10
Classifier: Programming Language :: Python :: 3.11
Classifier: Programming Language :: Python :: 3.12
Classifier: Programming Language :: Python :: 3.13
Classifier: Typing :: Typed
Requires-Python: >=3.10
Requires-Dist: mrcfile>=1.3.0
Requires-Dist: numpy>=1.19.0
Requires-Dist: pandas>=1.3.0
Requires-Dist: pydantic>=2.0.0
